sp_brew/Data_class.py
sp_brew/__init__.py
sp_brew/utils_files.py
sp_brew/utils_math.py
sp_brew/waveguide_module.py
sp_brew-0.1.12.dist-info/METADATA
sp_brew-0.1.12.dist-info/WHEEL
sp_brew-0.1.12.dist-info/entry_points.txt
sp_brew-0.1.12.dist-info/RECORD
