Metadata-Version: 2.4
Name: sp-brew
Version: 0.1.12
Summary: Module to visualize and extract information from raw data
Author-email: DMassella <damiano.massella@smartphotonics.nl>, CMattia <matta.conti@smartphotonics.nl>
Requires-Python: >=3.11
Requires-Dist: matplotlib>=3.9.4
Requires-Dist: numpy>=2.0.2
Requires-Dist: pandas>=2.2.3
Requires-Dist: scipy>=1.13.1
